ims_client/__init__.py
ims_client-0.1.16.dist-info/LICENSE
ims_client-0.1.16.dist-info/WHEEL
ims_client-0.1.16.dist-info/METADATA
ims_client-0.1.16.dist-info/RECORD
