Metadata-Version: 2.1
Name: ims_client
Version: 0.1.16
Summary: Simple python client for the capspire IMS Server
Home-page: UNKNOWN
License: UNKNOWN
Author: James Vogel
Author-email: jim.m.vogel@gmail.com
Requires-Python: >=3.5
Classifier: License :: OSI Approved :: MIT License
Requires-Dist: loguru
Requires-Dist: tenacity
Requires-Dist: pydantic
Requires-Dist: httpx
Requires-Dist: pytz
Requires-Dist: pytest-watch ; extra == "dev"
Requires-Dist: tomlkit ; extra == "dev"
Requires-Dist: black ; extra == "dev"
Requires-Dist: pytest ; extra == "test"
Requires-Dist: pytest-cov ; extra == "test"
Provides-Extra: dev
Provides-Extra: test
